{"v":5,"entries":{"components-button--docs":{"id":"components-button--docs","title":"Components/Button","name":"Docs","importPath":"./src/components/Button/Button.stories.tsx","type":"docs","tags":["dev","test","manifest","autodocs"],"storiesImports":[]},"components-button--red":{"type":"story","subtype":"story","id":"components-button--red","name":"Red","title":"Components/Button","importPath":"./src/components/Button/Button.stories.tsx","componentPath":"./src/components/Button/Button.tsx","tags":["dev","test","manifest","autodocs"],"exportName":"Red"},"components-button--green":{"type":"story","subtype":"story","id":"components-button--green","name":"Green","title":"Components/Button","importPath":"./src/components/Button/Button.stories.tsx","componentPath":"./src/components/Button/Button.tsx","tags":["dev","test","manifest","autodocs"],"exportName":"Green"},"components-button--blue":{"type":"story","subtype":"story","id":"components-button--blue","name":"Blue","title":"Components/Button","importPath":"./src/components/Button/Button.stories.tsx","componentPath":"./src/components/Button/Button.tsx","tags":["dev","test","manifest","autodocs"],"exportName":"Blue"},"components-button--disabled":{"type":"story","subtype":"story","id":"components-button--disabled","name":"Disabled","title":"Components/Button","importPath":"./src/components/Button/Button.stories.tsx","componentPath":"./src/components/Button/Button.tsx","tags":["dev","test","manifest","autodocs"],"exportName":"Disabled"}}}